plank/depot/__init__.py
plank/depot/storage/__init__.py
plank/depot/storage/dataframe.py
plank_extend_depot-0.1.0.dist-info/WHEEL
plank_extend_depot-0.1.0.dist-info/METADATA
plank_extend_depot-0.1.0.dist-info/RECORD
